rcps/__init__.py
rcps/core.py
rcps_pytorch-0.0.2.dist-info/LICENSE
rcps_pytorch-0.0.2.dist-info/METADATA
rcps_pytorch-0.0.2.dist-info/WHEEL
rcps_pytorch-0.0.2.dist-info/top_level.txt
rcps_pytorch-0.0.2.dist-info/RECORD
