Metadata-Version: 2.1
Name: rcps_pytorch
Version: 0.0.2
Summary: Reverse-complement parameter sharing (RCPS) layers for machine learning on DNA sequences in PyTorch 
Author-email: James Ashford <ashfordj@rocketmail.com>
Project-URL: Homepage, https://github.com/JELAshford/rcps-pytorch
Classifier: Programming Language :: Python :: 3
Classifier: License :: OSI Approved :: MIT License
Classifier: Operating System :: OS Independent
Requires-Python: >=3.8
License-File: LICENSE
Requires-Dist: einops >=0.6.1
Requires-Dist: torch
Requires-Dist: numpy <2
